src/__init__.py
src/cli.py
sampy_cli-0.1.dist-info/LICENSE
sampy_cli-0.1.dist-info/METADATA
sampy_cli-0.1.dist-info/WHEEL
sampy_cli-0.1.dist-info/entry_points.txt
sampy_cli-0.1.dist-info/top_level.txt
sampy_cli-0.1.dist-info/RECORD
